AUTHORS
CHANGELOG.txt
DESCRIPTION
LICENSE
MANIFEST.in
README.rst
setup.cfg
setup.py
aps_process/__init__.py
aps_process/admin.py
aps_process/models.py
aps_process/migrations/0001_initial.py
aps_process/migrations/__init__.py
aps_process/tests/.coveragerc
aps_process/tests/__init__.py
aps_process/tests/factories.py
aps_process/tests/models_tests.py
aps_process/tests/runtests.py
aps_process/tests/south_settings.py
aps_process/tests/test_settings.py
aps_process/tests/urls.py
django_aps_process.egg-info/PKG-INFO
django_aps_process.egg-info/SOURCES.txt
django_aps_process.egg-info/dependency_links.txt
django_aps_process.egg-info/requires.txt
django_aps_process.egg-info/top_level.txt