Metadata-Version: 1.0
Name: django-aps-process
Version: 0.1
Summary: The Process module for django-apsara
